evydcloud/__init__.py
evydcloud/connector_base.py
evydcloud/dbconnector.py
evydcloud/hive/__init__.py
evydcloud/hive/connector.py
evydcloud-1.0.0.dist-info/LICENSE
evydcloud-1.0.0.dist-info/METADATA
evydcloud-1.0.0.dist-info/WHEEL
evydcloud-1.0.0.dist-info/top_level.txt
evydcloud-1.0.0.dist-info/RECORD
