Metadata-Version: 2.1
Name: evydcloud
Version: 1.0.0
Summary: EvydenceCloud
Author: Yingjie Wang
Author-email: "yingjie.wang" <yingjie.wang@evydtech.com>
Project-URL: Homepage, https://git.evyd.tech/evydence/evydcloud
Classifier: Programming Language :: Python :: 3
Classifier: License :: OSI Approved :: MIT License
Classifier: Operating System :: OS Independent
Requires-Python: >=3.7
License-File: LICENSE
Requires-Dist: pandas
Requires-Dist: pyhive
Requires-Dist: pyjwt ==1.6.4
